Flask_Minio-0.1.2.dist-info/METADATA
Flask_Minio-0.1.2.dist-info/RECORD
Flask_Minio-0.1.2.dist-info/WHEEL
Flask_Minio-0.1.2.dist-info/top_level.txt
flask_minio/__init__.py
