Metadata-Version: 2.1
Name: Flask-Minio
Version: 0.1.2
Summary: Adds Minio support to your Flask application
Home-page: https://github.com/alejandroandreu/flask-minio
Author: Alejandro Andreu
Author-email: contact@alejandroandr.eu
License: BSD
Platform: any
Classifier: Environment :: Web Environment
Classifier: Intended Audience :: Developers
Classifier: License :: OSI Approved :: BSD License
Classifier: Operating System :: OS Independent
Classifier: Programming Language :: Python :: 3
Classifier: Topic :: Internet :: WWW/HTTP :: Dynamic Content
Classifier: Topic :: Software Development :: Libraries :: Python Modules
